{
    "faq": "None yet\n", 
    "tasks": [
        {
            "checklist": [
                "Produce at least one natural dye or bacterial dye.\n- Natural dye - modifying it\u2019s colour and mordanting it in different ways to dye at least 2 different categories of fibers\n- Bacterial dye - Explored dyeing with bacteria of different fibers and/or bacteria\n", 
                "Document your recipes, the ingredients and process and if there have been changes, document your unexpected discoveries", 
                "Submit some of your swatches to the analog material library of your lab. (20cm*20cm approx)"
            ], 
            "description": "", 
            "name": "Biochromes", 
            "outcomes": [
                "Master techniques for natural dyeing or bacterial dyeing", 
                "Documentation: Anyone can go through the process and use the recipes", 
                "Final outcome: create a color chart", 
                "Originality - Aesthetics: Has the design been thought through and elaborated"
            ]
        }
    ], 
    "version": 2020, 
    "unit": "Biochromes", 
    "unit_id": "biochromes"
}